mpstats/configs/__init__.py
mpstats/configs/logger_settings.py
mpstats/utils/__init__.py
mpstats/utils/main_utils.py
mpstats_library-0.1.0.dist-info/METADATA
mpstats_library-0.1.0.dist-info/WHEEL
mpstats_library-0.1.0.dist-info/top_level.txt
mpstats_library-0.1.0.dist-info/RECORD
