Metadata-Version: 2.4
Name: mpstats-library
Version: 0.1.0
Summary: Add your description here
Requires-Python: >=3.9
Requires-Dist: python-dotenv>=1.1.0
